molfeat_padel/__init__.py
molfeat_padel/calc/__init__.py
molfeat_padel/calc/padel.py
molfeat_padel-0.0.2.dist-info/LICENSE
molfeat_padel-0.0.2.dist-info/METADATA
molfeat_padel-0.0.2.dist-info/WHEEL
molfeat_padel-0.0.2.dist-info/entry_points.txt
molfeat_padel-0.0.2.dist-info/top_level.txt
molfeat_padel-0.0.2.dist-info/RECORD
