Metadata-Version: 2.1
Name: molfeat-padel
Version: 0.0.2
Summary: molfeat plugin to support featurization using Padel descriptors
Author-email: Emmanuel Noutahi <emmanuel.noutahi@hotmail.ca>
License: Apache
Project-URL: Website, https://molfeat.datamol.io
Project-URL: Source Code, https://github.com/datamol-io/molfeat-padel
Project-URL: Bug Tracker, https://github.com/datamol-io/molfeat-padel/issues
Project-URL: Documentation, https://molfeat-docs.datamol.io
Keywords: molfeat,plugin,PaDEL
Classifier: Development Status :: 3 - Alpha
Classifier: Intended Audience :: Developers
Classifier: Intended Audience :: Healthcare Industry
Classifier: Intended Audience :: Science/Research
Classifier: Topic :: Scientific/Engineering :: Artificial Intelligence
Classifier: Topic :: Scientific/Engineering :: Bio-Informatics
Classifier: Topic :: Scientific/Engineering :: Information Analysis
Classifier: Topic :: Scientific/Engineering :: Medical Science Apps.
Classifier: Natural Language :: English
Classifier: Operating System :: OS Independent
Classifier: Programming Language :: Python
Classifier: Programming Language :: Python :: 3
Classifier: Programming Language :: Python :: 3.8
Classifier: Programming Language :: Python :: 3.9
Classifier: Programming Language :: Python :: 3.10
Requires-Python: >=3.8
License-File: LICENSE
Requires-Dist: molfeat
Requires-Dist: padelpy
